{"Name":"aliar","EnglishMeaning":"to ally","PresentParticiple":"aliando","PastParticiple":"aliado","Indicative":{"PresentTense":{"Yo":"alio","Tu":"alias","ElEllaUsted":"alia","Nosotros":"aliamos","Vosotros":"aliáis","EllosEllasUstedes":"alian"},"Pretérito":{"Yo":"alié","Tu":"aliaste","ElEllaUsted":"alió","Nosotros":"aliamos","Vosotros":"aliasteis","EllosEllasUstedes":"aliaron"},"Conditional":{"Yo":"aliaría","Tu":"aliarías","ElEllaUsted":"aliaría","Nosotros":"aliaríamos","Vosotros":"aliaríais","EllosEllasUstedes":"aliarían"},"Future":{"Yo":"aliaré","Tu":"aliarás","ElEllaUsted":"aliará","Nosotros":"aliaremos","Vosotros":"aliaréis","EllosEllasUstedes":"aliarán"}},"Subjunctive":{"PresentTense":{"Yo":"alie","Tu":"alies","ElEllaUsted":"alie","Nosotros":"aliemos","Vosotros":"aliéis","EllosEllasUstedes":"alien"},"Imperfect":{"Yo":"aliaba","Tu":"aliabas","ElEllaUsted":"aliaba","Nosotros":"aliábamos","Vosotros":"aliabais","EllosEllasUstedes":"aliaban"},"Future":null}}