{"Name":"aparecer","EnglishMeaning":"to appear, show up","PresentParticiple":"apareciendo","PastParticiple":"aparecido","Indicative":{"PresentTense":{"Yo":"aparezco","Tu":"apareces","ElEllaUsted":"aparece","Nosotros":"aparecemos","Vosotros":"aparecéis","EllosEllasUstedes":"aparecen"},"Pretérito":{"Yo":"aparecí","Tu":"apareciste","ElEllaUsted":"apareció","Nosotros":"aparecimos","Vosotros":"aparecisteis","EllosEllasUstedes":"aparecieron"},"Conditional":{"Yo":"aparecería","Tu":"aparecerías","ElEllaUsted":"aparecería","Nosotros":"apareceríamos","Vosotros":"apareceríais","EllosEllasUstedes":"aparecerían"},"Future":{"Yo":"apareceré","Tu":"aparecerás","ElEllaUsted":"aparecerá","Nosotros":"apareceremos","Vosotros":"apareceréis","EllosEllasUstedes":"aparecerán"}},"Subjunctive":{"PresentTense":{"Yo":"aparezca","Tu":"aparezcas","ElEllaUsted":"aparezca","Nosotros":"aparezcamos","Vosotros":"aparezcáis","EllosEllasUstedes":"aparezcan"},"Imperfect":{"Yo":"aparecía","Tu":"aparecías","ElEllaUsted":"aparecía","Nosotros":"aparecíamos","Vosotros":"aparecíais","EllosEllasUstedes":"aparecían"},"Future":null}}