{"Name":"criticar","EnglishMeaning":"to criticize","PresentParticiple":"criticando","PastParticiple":"criticado","Indicative":{"PresentTense":{"Yo":"critico","Tu":"criticas","ElEllaUsted":"critica","Nosotros":"criticamos","Vosotros":"criticáis","EllosEllasUstedes":"critican"},"Pretérito":{"Yo":"critiqué","Tu":"criticaste","ElEllaUsted":"criticó","Nosotros":"criticamos","Vosotros":"criticasteis","EllosEllasUstedes":"criticaron"},"Conditional":{"Yo":"criticaría","Tu":"criticarías","ElEllaUsted":"criticaría","Nosotros":"criticaríamos","Vosotros":"criticaríais","EllosEllasUstedes":"criticarían"},"Future":{"Yo":"criticaré","Tu":"criticarás","ElEllaUsted":"criticará","Nosotros":"criticaremos","Vosotros":"criticaréis","EllosEllasUstedes":"criticarán"}},"Subjunctive":{"PresentTense":{"Yo":"critique","Tu":"critiques","ElEllaUsted":"critique","Nosotros":"critiquemos","Vosotros":"critiquéis","EllosEllasUstedes":"critiquen"},"Imperfect":{"Yo":"criticaba","Tu":"criticabas","ElEllaUsted":"criticaba","Nosotros":"criticábamos","Vosotros":"criticabais","EllosEllasUstedes":"criticaban"},"Future":null}}