{"Name":"emborrachar","EnglishMeaning":"to get drunk","PresentParticiple":"emborrachando","PastParticiple":"emborrachado","Indicative":{"PresentTense":{"Yo":"emborracho","Tu":"emborrachas","ElEllaUsted":"emborracha","Nosotros":"emborrachamos","Vosotros":"emborracháis","EllosEllasUstedes":"emborrachan"},"Pretérito":{"Yo":"emborraché","Tu":"emborrachaste","ElEllaUsted":"emborrachó","Nosotros":"emborrachamos","Vosotros":"emborrachasteis","EllosEllasUstedes":"emborracharon"},"Conditional":{"Yo":"emborracharía","Tu":"emborracharías","ElEllaUsted":"emborracharía","Nosotros":"emborracharíamos","Vosotros":"emborracharíais","EllosEllasUstedes":"emborracharían"},"Future":{"Yo":"emborracharé","Tu":"emborracharás","ElEllaUsted":"emborrachará","Nosotros":"emborracharemos","Vosotros":"emborracharéis","EllosEllasUstedes":"emborracharán"}},"Subjunctive":{"PresentTense":{"Yo":"emborrache","Tu":"emborraches","ElEllaUsted":"emborrache","Nosotros":"emborrachemos","Vosotros":"emborrachéis","EllosEllasUstedes":"emborrachen"},"Imperfect":{"Yo":"emborrachaba","Tu":"emborrachabas","ElEllaUsted":"emborrachaba","Nosotros":"emborrachábamos","Vosotros":"emborrachabais","EllosEllasUstedes":"emborrachaban"},"Future":null}}