{"Name":"evacuar","EnglishMeaning":"to evacuate; to fulfill","PresentParticiple":"evacuando","PastParticiple":"evacuado","Indicative":{"PresentTense":{"Yo":"evacúo","Tu":"evacúas","ElEllaUsted":"evacúa","Nosotros":"evacuamos","Vosotros":"evacuáis","EllosEllasUstedes":"evacúan"},"Pretérito":{"Yo":"evacué","Tu":"evacuaste","ElEllaUsted":"evacuó","Nosotros":"evacuamos","Vosotros":"evacuasteis","EllosEllasUstedes":"evacuaron"},"Conditional":{"Yo":"evacuaría","Tu":"evacuarías","ElEllaUsted":"evacuaría","Nosotros":"evacuaríamos","Vosotros":"evacuaríais","EllosEllasUstedes":"evacuarían"},"Future":{"Yo":"evacuaré","Tu":"evacuarás","ElEllaUsted":"evacuará","Nosotros":"evacuaremos","Vosotros":"evacuaréis","EllosEllasUstedes":"evacuarán"}},"Subjunctive":{"PresentTense":{"Yo":"evacúe","Tu":"evacúes","ElEllaUsted":"evacúe","Nosotros":"evacuemos","Vosotros":"evacuéis","EllosEllasUstedes":"evacúen"},"Imperfect":{"Yo":"evacuaba","Tu":"evacuabas","ElEllaUsted":"evacuaba","Nosotros":"evacuábamos","Vosotros":"evacuabais","EllosEllasUstedes":"evacuaban"},"Future":null}}