{"Name":"gemir","EnglishMeaning":"to groan, moan","PresentParticiple":"g<span class='conj-irregular'>i","PastParticiple":"gemido","Indicative":{"PresentTense":{"Yo":"gimo","Tu":"gimes","ElEllaUsted":"gime","Nosotros":"gemimos","Vosotros":"gemís","EllosEllasUstedes":"gimen"},"Pretérito":{"Yo":"gemí","Tu":"gemiste","ElEllaUsted":"gimió","Nosotros":"gemimos","Vosotros":"gemisteis","EllosEllasUstedes":"gimieron"},"Conditional":{"Yo":"gemiría","Tu":"gemirías","ElEllaUsted":"gemiría","Nosotros":"gemiríamos","Vosotros":"gemiríais","EllosEllasUstedes":"gemirían"},"Future":{"Yo":"gemiré","Tu":"gemirás","ElEllaUsted":"gemirá","Nosotros":"gemiremos","Vosotros":"gemiréis","EllosEllasUstedes":"gemirán"}},"Subjunctive":{"PresentTense":{"Yo":"gima","Tu":"gimas","ElEllaUsted":"gima","Nosotros":"gimamos","Vosotros":"gimáis","EllosEllasUstedes":"giman"},"Imperfect":{"Yo":"gemía","Tu":"gemías","ElEllaUsted":"gemía","Nosotros":"gemíamos","Vosotros":"gemíais","EllosEllasUstedes":"gemían"},"Future":null}}