{"Name":"huir","EnglishMeaning":"to flee, escape","PresentParticiple":"hu<span class='conj-irregular'>y","PastParticiple":"huido","Indicative":{"PresentTense":{"Yo":"huyo","Tu":"huyes","ElEllaUsted":"huye","Nosotros":"huimos","Vosotros":"huís","EllosEllasUstedes":"huyen"},"Pretérito":{"Yo":"huí","Tu":"huiste","ElEllaUsted":"huyó","Nosotros":"huimos","Vosotros":"huisteis","EllosEllasUstedes":"huyeron"},"Conditional":{"Yo":"huiría","Tu":"huirías","ElEllaUsted":"huiría","Nosotros":"huiríamos","Vosotros":"huiríais","EllosEllasUstedes":"huirían"},"Future":{"Yo":"huiré","Tu":"huirás","ElEllaUsted":"huirá","Nosotros":"huiremos","Vosotros":"huiréis","EllosEllasUstedes":"huirán"}},"Subjunctive":{"PresentTense":{"Yo":"huya","Tu":"huyas","ElEllaUsted":"huya","Nosotros":"huyamos","Vosotros":"huyáis","EllosEllasUstedes":"huyan"},"Imperfect":{"Yo":"huía","Tu":"huías","ElEllaUsted":"huía","Nosotros":"huíamos","Vosotros":"huíais","EllosEllasUstedes":"huían"},"Future":null}}