{"Name":"introducir","EnglishMeaning":"to introduce, insert, input","PresentParticiple":"introduciendo","PastParticiple":"introducido","Indicative":{"PresentTense":{"Yo":"introduzco","Tu":"introduces","ElEllaUsted":"introduce","Nosotros":"introducimos","Vosotros":"introducís","EllosEllasUstedes":"introducen"},"Pretérito":{"Yo":"introduje","Tu":"introdujiste","ElEllaUsted":"introdujo","Nosotros":"introdujimos","Vosotros":"introdujisteis","EllosEllasUstedes":"introdujeron"},"Conditional":{"Yo":"introduciría","Tu":"introducirías","ElEllaUsted":"introduciría","Nosotros":"introduciríamos","Vosotros":"introduciríais","EllosEllasUstedes":"introducirían"},"Future":{"Yo":"introduciré","Tu":"introducirás","ElEllaUsted":"introducirá","Nosotros":"introduciremos","Vosotros":"introduciréis","EllosEllasUstedes":"introducirán"}},"Subjunctive":{"PresentTense":{"Yo":"introduzca","Tu":"introduzcas","ElEllaUsted":"introduzca","Nosotros":"introduzcamos","Vosotros":"introduzcáis","EllosEllasUstedes":"introduzcan"},"Imperfect":{"Yo":"introducía","Tu":"introducías","ElEllaUsted":"introducía","Nosotros":"introducíamos","Vosotros":"introducíais","EllosEllasUstedes":"introducían"},"Future":null}}