{"Name":"plantar","EnglishMeaning":"to plant; to erect, set up","PresentParticiple":"plantando","PastParticiple":"plantado","Indicative":{"PresentTense":{"Yo":"planto","Tu":"plantas","ElEllaUsted":"planta","Nosotros":"plantamos","Vosotros":"plantáis","EllosEllasUstedes":"plantan"},"Pretérito":{"Yo":"planté","Tu":"plantaste","ElEllaUsted":"plantó","Nosotros":"plantamos","Vosotros":"plantasteis","EllosEllasUstedes":"plantaron"},"Conditional":{"Yo":"plantaría","Tu":"plantarías","ElEllaUsted":"plantaría","Nosotros":"plantaríamos","Vosotros":"plantaríais","EllosEllasUstedes":"plantarían"},"Future":{"Yo":"plantaré","Tu":"plantarás","ElEllaUsted":"plantará","Nosotros":"plantaremos","Vosotros":"plantaréis","EllosEllasUstedes":"plantarán"}},"Subjunctive":{"PresentTense":{"Yo":"plante","Tu":"plantes","ElEllaUsted":"plante","Nosotros":"plantemos","Vosotros":"plantéis","EllosEllasUstedes":"planten"},"Imperfect":{"Yo":"plantaba","Tu":"plantabas","ElEllaUsted":"plantaba","Nosotros":"plantábamos","Vosotros":"plantabais","EllosEllasUstedes":"plantaban"},"Future":null}}