{"Name":"planchar","EnglishMeaning":"to iron","PresentParticiple":"planchando","PastParticiple":"planchado","Indicative":{"PresentTense":{"Yo":"plancho","Tu":"planchas","ElEllaUsted":"plancha","Nosotros":"planchamos","Vosotros":"plancháis","EllosEllasUstedes":"planchan"},"Pretérito":{"Yo":"planché","Tu":"planchaste","ElEllaUsted":"planchó","Nosotros":"planchamos","Vosotros":"planchasteis","EllosEllasUstedes":"plancharon"},"Conditional":{"Yo":"plancharía","Tu":"plancharías","ElEllaUsted":"plancharía","Nosotros":"plancharíamos","Vosotros":"plancharíais","EllosEllasUstedes":"plancharían"},"Future":{"Yo":"plancharé","Tu":"plancharás","ElEllaUsted":"planchará","Nosotros":"plancharemos","Vosotros":"plancharéis","EllosEllasUstedes":"plancharán"}},"Subjunctive":{"PresentTense":{"Yo":"planche","Tu":"planches","ElEllaUsted":"planche","Nosotros":"planchemos","Vosotros":"planchéis","EllosEllasUstedes":"planchen"},"Imperfect":{"Yo":"planchaba","Tu":"planchabas","ElEllaUsted":"planchaba","Nosotros":"planchábamos","Vosotros":"planchabais","EllosEllasUstedes":"planchaban"},"Future":null}}