{"Name":"promover","EnglishMeaning":"to promote","PresentParticiple":"promoviendo","PastParticiple":"promovido","Indicative":{"PresentTense":{"Yo":"promuevo","Tu":"promueves","ElEllaUsted":"promueve","Nosotros":"promovemos","Vosotros":"promovéis","EllosEllasUstedes":"promueven"},"Pretérito":{"Yo":"promoví","Tu":"promoviste","ElEllaUsted":"promovió","Nosotros":"promovimos","Vosotros":"promovisteis","EllosEllasUstedes":"promovieron"},"Conditional":{"Yo":"promovería","Tu":"promoverías","ElEllaUsted":"promovería","Nosotros":"promoveríamos","Vosotros":"promoveríais","EllosEllasUstedes":"promoverían"},"Future":{"Yo":"promoveré","Tu":"promoverás","ElEllaUsted":"promoverá","Nosotros":"promoveremos","Vosotros":"promoveréis","EllosEllasUstedes":"promoverán"}},"Subjunctive":{"PresentTense":{"Yo":"promueva","Tu":"promuevas","ElEllaUsted":"promueva","Nosotros":"promovamos","Vosotros":"promováis","EllosEllasUstedes":"promuevan"},"Imperfect":{"Yo":"promovía","Tu":"promovías","ElEllaUsted":"promovía","Nosotros":"promovíamos","Vosotros":"promovíais","EllosEllasUstedes":"promovían"},"Future":null}}