{"Name":"recomenzar","EnglishMeaning":"to begin again, recommence","PresentParticiple":"recomenzando","PastParticiple":"recomenzado","Indicative":{"PresentTense":{"Yo":"recomienzo","Tu":"recomienzas","ElEllaUsted":"recomienza","Nosotros":"recomenzamos","Vosotros":"recomenzáis","EllosEllasUstedes":"recomienzan"},"Pretérito":{"Yo":"recomencé","Tu":"recomenzaste","ElEllaUsted":"recomenzó","Nosotros":"recomenzamos","Vosotros":"recomenzasteis","EllosEllasUstedes":"recomenzaron"},"Conditional":{"Yo":"recomenzaría","Tu":"recomenzarías","ElEllaUsted":"recomenzaría","Nosotros":"recomenzaríamos","Vosotros":"recomenzaríais","EllosEllasUstedes":"recomenzarían"},"Future":{"Yo":"recomenzaré","Tu":"recomenzarás","ElEllaUsted":"recomenzará","Nosotros":"recomenzaremos","Vosotros":"recomenzaréis","EllosEllasUstedes":"recomenzarán"}},"Subjunctive":{"PresentTense":{"Yo":"recomience","Tu":"recomiences","ElEllaUsted":"recomience","Nosotros":"recomencemos","Vosotros":"recomencéis","EllosEllasUstedes":"recomiencen"},"Imperfect":{"Yo":"recomenzaba","Tu":"recomenzabas","ElEllaUsted":"recomenzaba","Nosotros":"recomenzábamos","Vosotros":"recomenzabais","EllosEllasUstedes":"recomenzaban"},"Future":null}}