{"Name":"reconocer","EnglishMeaning":"to recognize, identify, acknowledge","PresentParticiple":"reconociendo","PastParticiple":"reconocido","Indicative":{"PresentTense":{"Yo":"reconozco","Tu":"reconoces","ElEllaUsted":"reconoce","Nosotros":"reconocemos","Vosotros":"reconocéis","EllosEllasUstedes":"reconocen"},"Pretérito":{"Yo":"reconocí","Tu":"reconociste","ElEllaUsted":"reconoció","Nosotros":"reconocimos","Vosotros":"reconocisteis","EllosEllasUstedes":"reconocieron"},"Conditional":{"Yo":"reconocería","Tu":"reconocerías","ElEllaUsted":"reconocería","Nosotros":"reconoceríamos","Vosotros":"reconoceríais","EllosEllasUstedes":"reconocerían"},"Future":{"Yo":"reconoceré","Tu":"reconocerás","ElEllaUsted":"reconocerá","Nosotros":"reconoceremos","Vosotros":"reconoceréis","EllosEllasUstedes":"reconocerán"}},"Subjunctive":{"PresentTense":{"Yo":"reconozca","Tu":"reconozcas","ElEllaUsted":"reconozca","Nosotros":"reconozcamos","Vosotros":"reconozcáis","EllosEllasUstedes":"reconozcan"},"Imperfect":{"Yo":"reconocía","Tu":"reconocías","ElEllaUsted":"reconocía","Nosotros":"reconocíamos","Vosotros":"reconocíais","EllosEllasUstedes":"reconocían"},"Future":null}}