{"Name":"relajar","EnglishMeaning":"to relax","PresentParticiple":"relajando","PastParticiple":"relajado","Indicative":{"PresentTense":{"Yo":"relajo","Tu":"relajas","ElEllaUsted":"relaja","Nosotros":"relajamos","Vosotros":"relajáis","EllosEllasUstedes":"relajan"},"Pretérito":{"Yo":"relajé","Tu":"relajaste","ElEllaUsted":"relajó","Nosotros":"relajamos","Vosotros":"relajasteis","EllosEllasUstedes":"relajaron"},"Conditional":{"Yo":"relajaría","Tu":"relajarías","ElEllaUsted":"relajaría","Nosotros":"relajaríamos","Vosotros":"relajaríais","EllosEllasUstedes":"relajarían"},"Future":{"Yo":"relajaré","Tu":"relajarás","ElEllaUsted":"relajará","Nosotros":"relajaremos","Vosotros":"relajaréis","EllosEllasUstedes":"relajarán"}},"Subjunctive":{"PresentTense":{"Yo":"relaje","Tu":"relajes","ElEllaUsted":"relaje","Nosotros":"relajemos","Vosotros":"relajéis","EllosEllasUstedes":"relajen"},"Imperfect":{"Yo":"relajaba","Tu":"relajabas","ElEllaUsted":"relajaba","Nosotros":"relajábamos","Vosotros":"relajabais","EllosEllasUstedes":"relajaban"},"Future":null}}