{"Name":"residir","EnglishMeaning":"to reside","PresentParticiple":"residiendo","PastParticiple":"residido","Indicative":{"PresentTense":{"Yo":"resido","Tu":"resides","ElEllaUsted":"reside","Nosotros":"residimos","Vosotros":"residís","EllosEllasUstedes":"residen"},"Pretérito":{"Yo":"residí","Tu":"residiste","ElEllaUsted":"residió","Nosotros":"residimos","Vosotros":"residisteis","EllosEllasUstedes":"residieron"},"Conditional":{"Yo":"residiría","Tu":"residirías","ElEllaUsted":"residiría","Nosotros":"residiríamos","Vosotros":"residiríais","EllosEllasUstedes":"residirían"},"Future":{"Yo":"residiré","Tu":"residirás","ElEllaUsted":"residirá","Nosotros":"residiremos","Vosotros":"residiréis","EllosEllasUstedes":"residirán"}},"Subjunctive":{"PresentTense":{"Yo":"resida","Tu":"residas","ElEllaUsted":"resida","Nosotros":"residamos","Vosotros":"residáis","EllosEllasUstedes":"residan"},"Imperfect":{"Yo":"residía","Tu":"residías","ElEllaUsted":"residía","Nosotros":"residíamos","Vosotros":"residíais","EllosEllasUstedes":"residían"},"Future":null}}