{"Name":"saturar","EnglishMeaning":"to saturate","PresentParticiple":"saturando","PastParticiple":"saturado","Indicative":{"PresentTense":{"Yo":"saturo","Tu":"saturas","ElEllaUsted":"satura","Nosotros":"saturamos","Vosotros":"saturáis","EllosEllasUstedes":"saturan"},"Pretérito":{"Yo":"saturé","Tu":"saturaste","ElEllaUsted":"saturó","Nosotros":"saturamos","Vosotros":"saturasteis","EllosEllasUstedes":"saturaron"},"Conditional":{"Yo":"saturaría","Tu":"saturarías","ElEllaUsted":"saturaría","Nosotros":"saturaríamos","Vosotros":"saturaríais","EllosEllasUstedes":"saturarían"},"Future":{"Yo":"saturaré","Tu":"saturarás","ElEllaUsted":"saturará","Nosotros":"saturaremos","Vosotros":"saturaréis","EllosEllasUstedes":"saturarán"}},"Subjunctive":{"PresentTense":{"Yo":"sature","Tu":"satures","ElEllaUsted":"sature","Nosotros":"saturemos","Vosotros":"saturéis","EllosEllasUstedes":"saturen"},"Imperfect":{"Yo":"saturaba","Tu":"saturabas","ElEllaUsted":"saturaba","Nosotros":"saturábamos","Vosotros":"saturabais","EllosEllasUstedes":"saturaban"},"Future":null}}