{"Name":"situar","EnglishMeaning":"to put, place; to locate; to invest","PresentParticiple":"situando","PastParticiple":"situado","Indicative":{"PresentTense":{"Yo":"sitúo","Tu":"sitúas","ElEllaUsted":"sitúa","Nosotros":"situamos","Vosotros":"situáis","EllosEllasUstedes":"sitúan"},"Pretérito":{"Yo":"situé","Tu":"situaste","ElEllaUsted":"situó","Nosotros":"situamos","Vosotros":"situasteis","EllosEllasUstedes":"situaron"},"Conditional":{"Yo":"situaría","Tu":"situarías","ElEllaUsted":"situaría","Nosotros":"situaríamos","Vosotros":"situaríais","EllosEllasUstedes":"situarían"},"Future":{"Yo":"situaré","Tu":"situarás","ElEllaUsted":"situará","Nosotros":"situaremos","Vosotros":"situaréis","EllosEllasUstedes":"situarán"}},"Subjunctive":{"PresentTense":{"Yo":"sitúe","Tu":"sitúes","ElEllaUsted":"sitúe","Nosotros":"situemos","Vosotros":"situéis","EllosEllasUstedes":"sitúen"},"Imperfect":{"Yo":"situaba","Tu":"situabas","ElEllaUsted":"situaba","Nosotros":"situábamos","Vosotros":"situabais","EllosEllasUstedes":"situaban"},"Future":null}}