{"Name":"sonar","EnglishMeaning":"to sound, ring","PresentParticiple":"sonando","PastParticiple":"sonado","Indicative":{"PresentTense":{"Yo":"sueno","Tu":"suenas","ElEllaUsted":"suena","Nosotros":"sonamos","Vosotros":"sonáis","EllosEllasUstedes":"suenan"},"Pretérito":{"Yo":"soné","Tu":"sonaste","ElEllaUsted":"sonó","Nosotros":"sonamos","Vosotros":"sonasteis","EllosEllasUstedes":"sonaron"},"Conditional":{"Yo":"sonaría","Tu":"sonarías","ElEllaUsted":"sonaría","Nosotros":"sonaríamos","Vosotros":"sonaríais","EllosEllasUstedes":"sonarían"},"Future":{"Yo":"sonaré","Tu":"sonarás","ElEllaUsted":"sonará","Nosotros":"sonaremos","Vosotros":"sonaréis","EllosEllasUstedes":"sonarán"}},"Subjunctive":{"PresentTense":{"Yo":"suene","Tu":"suenes","ElEllaUsted":"suene","Nosotros":"sonemos","Vosotros":"sonéis","EllosEllasUstedes":"suenen"},"Imperfect":{"Yo":"sonaba","Tu":"sonabas","ElEllaUsted":"sonaba","Nosotros":"sonábamos","Vosotros":"sonabais","EllosEllasUstedes":"sonaban"},"Future":null}}